PyQRibbon/__init__.py
PyQRibbon/__version__.py
PyQRibbon/ribbon.py
PyQRibbon/utils.py
PyQRibbon/i18n/__init__.py
PyQRibbon/i18n/zh.json
PyQRibbon/theme/__init__.py
PyQRibbon/theme/default.qss
PyQRibbon/theme/images/fixed.png
PyQRibbon/theme/images/fold.png
PyQRibbon/widgets/__init__.py
PyQRibbon/widgets/framelessWindow.py
PyQRibbon/widgets/ribbonWidget.py
PyQRibbon-0.9.8.dist-info/LICENSE
PyQRibbon-0.9.8.dist-info/METADATA
PyQRibbon-0.9.8.dist-info/WHEEL
PyQRibbon-0.9.8.dist-info/top_level.txt
PyQRibbon-0.9.8.dist-info/RECORD
