Metadata-Version: 2.1
Name: PyQRibbon
Version: 0.9.8
Summary: PyQRibbon
Home-page: https://github.com/luolingchun/PyQRibbon
Author: llc
Author-email: luolingchun@outlook.com
License: GPLv3
Platform: any
Requires-Python: >=3.6
Requires-Dist: PyQt5
